pixsaw/__init__.py
pixsaw/_version.py
pixsaw/base.py
pixsaw/scratch
pixsaw/script.py
pixsaw/tools.py
pixsaw-0.6.0.dist-info/METADATA
pixsaw-0.6.0.dist-info/WHEEL
pixsaw-0.6.0.dist-info/entry_points.txt
pixsaw-0.6.0.dist-info/licenses/COPYING
pixsaw-0.6.0.dist-info/licenses/COPYING.LESSER
pixsaw-0.6.0.dist-info/RECORD
