Metadata-Version: 2.4
Name: pixsaw
Version: 0.6.0
Summary: Cut a picture into pieces by cutting along pixel lines
Project-URL: Homepage, https://github.com/jkenlooper/pixsaw
Author-email: Jake Hickenlooper <jake@weboftomorrow.com>
License: LGPLv3+
License-File: COPYING
License-File: COPYING.LESSER
Requires-Python: <4,>=3.8
Requires-Dist: pillow<11,>=8.4.0
Provides-Extra: dev
Provides-Extra: test
Requires-Dist: coverage; extra == 'test'
Requires-Dist: pytest; extra == 'test'
